{"Id":"3fcec839-5796-48c9-a80c-fea2de032239","AppName":"socialheit.com","DoaminName":"socialheit","Formname":"test","ModelName":"ModelName","CreateEndpoint":"","UpdateEndpoint":"","GetEndpoint":"","GetRawQuery":"","DeleteEndpoint":"","ListEndpoint":"","saveBtnKeyForEditMode":"","CreateEndpointParams":[],"UpdateEndpointParams":[],"GetEndpointParams":[],"DeleteEndpointParams":[],"ListEndpointParams":[],"controls":[{"key":"Formwizard","Name":"Form wizard","label":"Form wizard","Totalstep":"0","icon":"fa fa-magic","type":"formwizard","width":12,"order":2,"showinlist":false,"haschildren":true,"hasdatasource":false,"isTableView":false,"children":[{"key":"Step","Header":"Property","label":"Property","icon":"tab_unselected","type":"tabcontainer","haschildren":true,"hasdatasource":false,"hideonedit":false,"children":[{"id":"11ba0f53-1ee3-38cc-b6e4-ac1e7fa3fa72","key":"key","Name":"Textbox","label":"Attributes","placeholder":"Attributes","icon":"fa fa-text-width","type":"textbox","width":"12","order":1,"require":false,"showinlist":true,"addinfilter":false,"filterheader":"","haschildren":false,"isTableView":false,"hasdatasource":false,"filterresult":false,"uuid":8300866885904,"errormsg":"","apiurl":"","queryfield":"","outputfield":"","apiparam":[]},{"id":"4c625f57-9de2-6c0c-308d-7723d12510a5","key":"titlemodel","Name":"Textbox","label":"Title Field Name","placeholder":"Title Field Name","icon":"fa fa-text-width","type":"textbox","width":"12","order":2,"require":false,"showinlist":true,"addinfilter":false,"filterheader":"","haschildren":false,"isTableView":false,"hasdatasource":false,"filterresult":false,"uuid":5800269351595,"errormsg":"","apiurl":"","queryfield":"","outputfield":"","apiparam":[]},{"id":"287bf0f2-3d5c-c2c0-d2db-e4ed80df7207","key":"subtitlemodel","Name":"Textbox","label":"Sub Title Field Name","placeholder":"Sub Title Field Name","icon":"fa fa-text-width","type":"textbox","width":"12","order":3,"require":false,"showinlist":true,"addinfilter":false,"filterheader":"","haschildren":false,"isTableView":false,"hasdatasource":false,"filterresult":false,"uuid":5434350726394,"errormsg":"","apiurl":"","queryfield":"","outputfield":"","apiparam":[]},{"id":"888a550e-43c4-dc89-266c-67e9324cf1d8","key":"icon","Name":"Textbox","label":"Icon css","placeholder":"","icon":"fa fa-text-width","type":"textbox","width":"12","order":4,"require":false,"showinlist":true,"addinfilter":false,"filterheader":"","haschildren":false,"isTableView":false,"hasdatasource":false,"filterresult":false,"uuid":2452840983673,"errormsg":"","apiurl":"","queryfield":"","outputfield":"","apiparam":[]}],"uuid":8147719104666,"require":false,"imageUrl":"","errormsg":"","formid":"","formactiontype":""},{"key":"Step","Header":"View","label":"View","icon":"tab_unselected","type":"tabcontainer","haschildren":true,"hasdatasource":false,"hideonedit":false,"children":[{"id":"219be209-c676-9bfe-2a50-14d90b7d3394","key":"label","Name":"Textbox","label":"Button Text","placeholder":"Button Text","icon":"fa fa-text-width","type":"textbox","width":"12","order":1,"require":false,"showinlist":true,"addinfilter":false,"filterheader":"","haschildren":false,"isTableView":false,"hasdatasource":false,"filterresult":false,"uuid":3545414154300},{"key":"WebIcon","Name":"Dropdown 2","label":"Web Icon","placeholder":"Web Icon","icon":"fa fa-chevron-circle-down","type":"dropdown2","width":"12","order":1,"require":false,"showinlist":true,"haschildren":false,"isTableView":false,"hasdatasource":false,"allowbindingwithcontrols":false,"bindingwithothercontrols":[],"refreshfromparent":false,"parentcontrolkey":"","apifieldforparentcontrol":"","addinfilter":false,"filterheader":"","autoselectfirstvalue":false,"textfield":"key","valuefield":"value","apiurl":"","ApiParam":[],"optionlist":[{"key":"500px","value":"fa fa-500px","groupkey":"","populatejson":""},{"key":"address-book","value":"fa fa-address-book","groupkey":"","populatejson":""},{"key":"address-book-o","value":"fa fa-address-book-o","groupkey":"","populatejson":""},{"key":"address-card","value":"fa fa-address-card","groupkey":"","populatejson":""},{"key":"address-card-o","value":"fa fa-address-card-o","groupkey":"","populatejson":""},{"key":"adjust","value":"fa fa-adjust","groupkey":"","populatejson":""},{"key":"adn","value":"fa fa-adn","groupkey":"","populatejson":""},{"key":"align-center","value":"fa fa-align-center","groupkey":"","populatejson":""},{"key":"align-justify","value":"fa fa-align-justify","groupkey":"","populatejson":""},{"key":"align-left","value":"fa fa-align-left","groupkey":"","populatejson":""},{"key":"align-right","value":"fa fa-align-right","groupkey":"","populatejson":""},{"key":"amazon","value":"fa fa-amazon","groupkey":"","populatejson":""},{"key":"ambulance","value":"fa fa-ambulance","groupkey":"","populatejson":""},{"key":"american-sign-language-interpreting","value":"fa fa-american-sign-language-interpreting","groupkey":"","populatejson":""},{"key":"anchor","value":"fa fa-anchor","groupkey":"","populatejson":""},{"key":"android","value":"fa fa-android","groupkey":"","populatejson":""},{"key":"angellist","value":"fa fa-angellist","groupkey":"","populatejson":""},{"key":"angle-double-down","value":"fa fa-angle-double-down","groupkey":"","populatejson":""},{"key":"angle-double-left","value":"fa fa-angle-double-left","groupkey":"","populatejson":""},{"key":"angle-double-right","value":"fa fa-angle-double-right","groupkey":"","populatejson":""},{"key":"angle-double-up","value":"fa fa-angle-double-up","groupkey":"","populatejson":""},{"key":"angle-down","value":"fa fa-angle-down","groupkey":"","populatejson":""},{"key":"angle-left","value":"fa fa-angle-left","groupkey":"","populatejson":""},{"key":"angle-right","value":"fa fa-angle-right","groupkey":"","populatejson":""},{"key":"angle-up","value":"fa fa-angle-up","groupkey":"","populatejson":""},{"key":"apple","value":"fa fa-apple","groupkey":"","populatejson":""},{"key":"archive","value":"fa fa-archive","groupkey":"","populatejson":""},{"key":"area-chart","value":"fa fa-area-chart","groupkey":"","populatejson":""},{"key":"arrow-circle-down","value":"fa fa-arrow-circle-down","groupkey":"","populatejson":""},{"key":"arrow-circle-left","value":"fa fa-arrow-circle-left","groupkey":"","populatejson":""},{"key":"arrow-circle-o-down","value":"fa fa-arrow-circle-o-down","groupkey":"","populatejson":""},{"key":"arrow-circle-o-left","value":"fa fa-arrow-circle-o-left","groupkey":"","populatejson":""},{"key":"arrow-circle-o-right","value":"fa fa-arrow-circle-o-right","groupkey":"","populatejson":""},{"key":"arrow-circle-o-up","value":"fa fa-arrow-circle-o-up","groupkey":"","populatejson":""},{"key":"arrow-circle-right","value":"fa fa-arrow-circle-right","groupkey":"","populatejson":""},{"key":"arrow-circle-up","value":"fa fa-arrow-circle-up","groupkey":"","populatejson":""},{"key":"arrow-down","value":"fa fa-arrow-down","groupkey":"","populatejson":""},{"key":"arrow-left","value":"fa fa-arrow-left","groupkey":"","populatejson":""},{"key":"arrow-right","value":"fa fa-arrow-right","groupkey":"","populatejson":""},{"key":"arrow-up","value":"fa fa-arrow-up","groupkey":"","populatejson":""},{"key":"arrows","value":"fa fa-arrows","groupkey":"","populatejson":""},{"key":"arrows-alt","value":"fa fa-arrows-alt","groupkey":"","populatejson":""},{"key":"arrows-h","value":"fa fa-arrows-h","groupkey":"","populatejson":""},{"key":"arrows-v","value":"fa fa-arrows-v","groupkey":"","populatejson":""},{"key":"asl-interpreting","value":"fa fa-asl-interpreting","groupkey":"","populatejson":""},{"key":"assistive-listening-systems","value":"fa fa-assistive-listening-systems","groupkey":"","populatejson":""},{"key":"asterisk","value":"fa fa-asterisk","groupkey":"","populatejson":""},{"key":"at","value":"fa fa-at","groupkey":"","populatejson":""},{"key":"audio-description","value":"fa fa-audio-description","groupkey":"","populatejson":""},{"key":"automobile","value":"fa fa-automobile","groupkey":"","populatejson":""},{"key":"backward","value":"fa fa-backward","groupkey":"","populatejson":""},{"key":"balance-scale","value":"fa fa-balance-scale","groupkey":"","populatejson":""},{"key":"ban","value":"fa fa-ban","groupkey":"","populatejson":""},{"key":"bandcamp","value":"fa fa-bandcamp","groupkey":"","populatejson":""},{"key":"bank","value":"fa fa-bank","groupkey":"","populatejson":""},{"key":"bar-chart","value":"fa fa-bar-chart","groupkey":"","populatejson":""},{"key":"bar-chart-o","value":"fa fa-bar-chart-o","groupkey":"","populatejson":""},{"key":"barcode","value":"fa fa-barcode","groupkey":"","populatejson":""},{"key":"bars","value":"fa fa-bars","groupkey":"","populatejson":""},{"key":"bath","value":"fa fa-bath","groupkey":"","populatejson":""},{"key":"bathtub","value":"fa fa-bathtub","groupkey":"","populatejson":""},{"key":"battery","value":"fa fa-battery","groupkey":"","populatejson":""},{"key":"battery-0","value":"fa fa-battery-0","groupkey":"","populatejson":""},{"key":"battery-1","value":"fa fa-battery-1","groupkey":"","populatejson":""},{"key":"battery-2","value":"fa fa-battery-2","groupkey":"","populatejson":""},{"key":"battery-3","value":"fa fa-battery-3","groupkey":"","populatejson":""},{"key":"battery-4","value":"fa fa-battery-4","groupkey":"","populatejson":""},{"key":"battery-empty","value":"fa fa-battery-empty","groupkey":"","populatejson":""},{"key":"battery-full","value":"fa fa-battery-full","groupkey":"","populatejson":""},{"key":"battery-half","value":"fa fa-battery-half","groupkey":"","populatejson":""},{"key":"battery-quarter","value":"fa fa-battery-quarter","groupkey":"","populatejson":""},{"key":"battery-three-quarters","value":"fa fa-battery-three-quarters","groupkey":"","populatejson":""},{"key":"bed","value":"fa fa-bed","groupkey":"","populatejson":""},{"key":"beer","value":"fa fa-beer","groupkey":"","populatejson":""},{"key":"behance","value":"fa fa-behance","groupkey":"","populatejson":""},{"key":"behance-square","value":"fa fa-behance-square","groupkey":"","populatejson":""},{"key":"bell","value":"fa fa-bell","groupkey":"","populatejson":""},{"key":"bell-o","value":"fa fa-bell-o","groupkey":"","populatejson":""},{"key":"bell-slash","value":"fa fa-bell-slash","groupkey":"","populatejson":""},{"key":"bell-slash-o","value":"fa fa-bell-slash-o","groupkey":"","populatejson":""},{"key":"bicycle","value":"fa fa-bicycle","groupkey":"","populatejson":""},{"key":"binoculars","value":"fa fa-binoculars","groupkey":"","populatejson":""},{"key":"birthday-cake","value":"fa fa-birthday-cake","groupkey":"","populatejson":""},{"key":"bitbucket","value":"fa fa-bitbucket","groupkey":"","populatejson":""},{"key":"bitbucket-square","value":"fa fa-bitbucket-square","groupkey":"","populatejson":""},{"key":"bitcoin","value":"fa fa-bitcoin","groupkey":"","populatejson":""},{"key":"black-tie","value":"fa fa-black-tie","groupkey":"","populatejson":""},{"key":"blind","value":"fa fa-blind","groupkey":"","populatejson":""},{"key":"bluetooth","value":"fa fa-bluetooth","groupkey":"","populatejson":""},{"key":"bluetooth-b","value":"fa fa-bluetooth-b","groupkey":"","populatejson":""},{"key":"bold","value":"fa fa-bold","groupkey":"","populatejson":""},{"key":"bolt","value":"fa fa-bolt","groupkey":"","populatejson":""},{"key":"bomb","value":"fa fa-bomb","groupkey":"","populatejson":""},{"key":"book","value":"fa fa-book","groupkey":"","populatejson":""},{"key":"bookmark","value":"fa fa-bookmark","groupkey":"","populatejson":""},{"key":"bookmark-o","value":"fa fa-bookmark-o","groupkey":"","populatejson":""},{"key":"braille","value":"fa fa-braille","groupkey":"","populatejson":""},{"key":"briefcase","value":"fa fa-briefcase","groupkey":"","populatejson":""},{"key":"btc","value":"fa fa-btc","groupkey":"","populatejson":""},{"key":"bug","value":"fa fa-bug","groupkey":"","populatejson":""},{"key":"building","value":"fa fa-building","groupkey":"","populatejson":""},{"key":"building-o","value":"fa fa-building-o","groupkey":"","populatejson":""},{"key":"bullhorn","value":"fa fa-bullhorn","groupkey":"","populatejson":""},{"key":"bullseye","value":"fa fa-bullseye","groupkey":"","populatejson":""},{"key":"bus","value":"fa fa-bus","groupkey":"","populatejson":""},{"key":"buysellads","value":"fa fa-buysellads","groupkey":"","populatejson":""},{"key":"cab","value":"fa fa-cab","groupkey":"","populatejson":""},{"key":"calculator","value":"fa fa-calculator","groupkey":"","populatejson":""},{"key":"calendar","value":"fa fa-calendar","groupkey":"","populatejson":""},{"key":"calendar-check-o","value":"fa fa-calendar-check-o","groupkey":"","populatejson":""},{"key":"calendar-minus-o","value":"fa fa-calendar-minus-o","groupkey":"","populatejson":""},{"key":"calendar-o","value":"fa fa-calendar-o","groupkey":"","populatejson":""},{"key":"calendar-plus-o","value":"fa fa-calendar-plus-o","groupkey":"","populatejson":""},{"key":"calendar-times-o","value":"fa fa-calendar-times-o","groupkey":"","populatejson":""},{"key":"camera","value":"fa fa-camera","groupkey":"","populatejson":""},{"key":"camera-retro","value":"fa fa-camera-retro","groupkey":"","populatejson":""},{"key":"car","value":"fa fa-car","groupkey":"","populatejson":""},{"key":"caret-down","value":"fa fa-caret-down","groupkey":"","populatejson":""},{"key":"caret-left","value":"fa fa-caret-left","groupkey":"","populatejson":""},{"key":"caret-right","value":"fa fa-caret-right","groupkey":"","populatejson":""},{"key":"caret-square-o-down","value":"fa fa-caret-square-o-down","groupkey":"","populatejson":""},{"key":"caret-square-o-left","value":"fa fa-caret-square-o-left","groupkey":"","populatejson":""},{"key":"caret-square-o-right","value":"fa fa-caret-square-o-right","groupkey":"","populatejson":""},{"key":"caret-square-o-up","value":"fa fa-caret-square-o-up","groupkey":"","populatejson":""},{"key":"caret-up","value":"fa fa-caret-up","groupkey":"","populatejson":""},{"key":"cart-arrow-down","value":"fa fa-cart-arrow-down","groupkey":"","populatejson":""},{"key":"cart-plus","value":"fa fa-cart-plus","groupkey":"","populatejson":""},{"key":"cc","value":"fa fa-cc","groupkey":"","populatejson":""},{"key":"cc-amex","value":"fa fa-cc-amex","groupkey":"","populatejson":""},{"key":"cc-diners-club","value":"fa fa-cc-diners-club","groupkey":"","populatejson":""},{"key":"cc-discover","value":"fa fa-cc-discover","groupkey":"","populatejson":""},{"key":"cc-jcb","value":"fa fa-cc-jcb","groupkey":"","populatejson":""},{"key":"cc-mastercard","value":"fa fa-cc-mastercard","groupkey":"","populatejson":""},{"key":"cc-paypal","value":"fa fa-cc-paypal","groupkey":"","populatejson":""},{"key":"cc-stripe","value":"fa fa-cc-stripe","groupkey":"","populatejson":""},{"key":"cc-visa","value":"fa fa-cc-visa","groupkey":"","populatejson":""},{"key":"certificate","value":"fa fa-certificate","groupkey":"","populatejson":""},{"key":"chain","value":"fa fa-chain","groupkey":"","populatejson":""},{"key":"chain-broken","value":"fa fa-chain-broken","groupkey":"","populatejson":""},{"key":"check","value":"fa fa-check","groupkey":"","populatejson":""},{"key":"check-circle","value":"fa fa-check-circle","groupkey":"","populatejson":""},{"key":"check-circle-o","value":"fa fa-check-circle-o","groupkey":"","populatejson":""},{"key":"check-square","value":"fa fa-check-square","groupkey":"","populatejson":""},{"key":"check-square-o","value":"fa fa-check-square-o","groupkey":"","populatejson":""},{"key":"chevron-circle-down","value":"fa fa-chevron-circle-down","groupkey":"","populatejson":""},{"key":"chevron-circle-left","value":"fa fa-chevron-circle-left","groupkey":"","populatejson":""},{"key":"chevron-circle-right","value":"fa fa-chevron-circle-right","groupkey":"","populatejson":""},{"key":"chevron-circle-up","value":"fa fa-chevron-circle-up","groupkey":"","populatejson":""},{"key":"chevron-down","value":"fa fa-chevron-down","groupkey":"","populatejson":""},{"key":"chevron-left","value":"fa fa-chevron-left","groupkey":"","populatejson":""},{"key":"chevron-right","value":"fa fa-chevron-right","groupkey":"","populatejson":""},{"key":"chevron-up","value":"fa fa-chevron-up","groupkey":"","populatejson":""},{"key":"child","value":"fa fa-child","groupkey":"","populatejson":""},{"key":"chrome","value":"fa fa-chrome","groupkey":"","populatejson":""},{"key":"circle","value":"fa fa-circle","groupkey":"","populatejson":""},{"key":"circle-o","value":"fa fa-circle-o","groupkey":"","populatejson":""},{"key":"circle-o-notch","value":"fa fa-circle-o-notch","groupkey":"","populatejson":""},{"key":"circle-thin","value":"fa fa-circle-thin","groupkey":"","populatejson":""},{"key":"clipboard","value":"fa fa-clipboard","groupkey":"","populatejson":""},{"key":"clock-o","value":"fa fa-clock-o","groupkey":"","populatejson":""},{"key":"clone","value":"fa fa-clone","groupkey":"","populatejson":""},{"key":"close","value":"fa fa-close","groupkey":"","populatejson":""},{"key":"cloud","value":"fa fa-cloud","groupkey":"","populatejson":""},{"key":"cloud-download","value":"fa fa-cloud-download","groupkey":"","populatejson":""},{"key":"cloud-upload","value":"fa fa-cloud-upload","groupkey":"","populatejson":""},{"key":"cny","value":"fa fa-cny","groupkey":"","populatejson":""},{"key":"code","value":"fa fa-code","groupkey":"","populatejson":""},{"key":"code-fork","value":"fa fa-code-fork","groupkey":"","populatejson":""},{"key":"codepen","value":"fa fa-codepen","groupkey":"","populatejson":""},{"key":"codiepie","value":"fa fa-codiepie","groupkey":"","populatejson":""},{"key":"coffee","value":"fa fa-coffee","groupkey":"","populatejson":""},{"key":"cog","value":"fa fa-cog","groupkey":"","populatejson":""},{"key":"cogs","value":"fa fa-cogs","groupkey":"","populatejson":""},{"key":"columns","value":"fa fa-columns","groupkey":"","populatejson":""},{"key":"comment","value":"fa fa-comment","groupkey":"","populatejson":""},{"key":"comment-o","value":"fa fa-comment-o","groupkey":"","populatejson":""},{"key":"commenting","value":"fa fa-commenting","groupkey":"","populatejson":""},{"key":"commenting-o","value":"fa fa-commenting-o","groupkey":"","populatejson":""},{"key":"comments","value":"fa fa-comments","groupkey":"","populatejson":""},{"key":"comments-o","value":"fa fa-comments-o","groupkey":"","populatejson":""},{"key":"compass","value":"fa fa-compass","groupkey":"","populatejson":""},{"key":"compress","value":"fa fa-compress","groupkey":"","populatejson":""},{"key":"connectdevelop","value":"fa fa-connectdevelop","groupkey":"","populatejson":""},{"key":"contao","value":"fa fa-contao","groupkey":"","populatejson":""},{"key":"copy","value":"fa fa-copy","groupkey":"","populatejson":""},{"key":"copyright","value":"fa fa-copyright","groupkey":"","populatejson":""},{"key":"creative-commons","value":"fa fa-creative-commons","groupkey":"","populatejson":""},{"key":"credit-card","value":"fa fa-credit-card","groupkey":"","populatejson":""},{"key":"credit-card-alt","value":"fa fa-credit-card-alt","groupkey":"","populatejson":""},{"key":"crop","value":"fa fa-crop","groupkey":"","populatejson":""},{"key":"crosshairs","value":"fa fa-crosshairs","groupkey":"","populatejson":""},{"key":"css3","value":"fa fa-css3","groupkey":"","populatejson":""},{"key":"cube","value":"fa fa-cube","groupkey":"","populatejson":""},{"key":"cubes","value":"fa fa-cubes","groupkey":"","populatejson":""},{"key":"cut","value":"fa fa-cut","groupkey":"","populatejson":""},{"key":"cutlery","value":"fa fa-cutlery","groupkey":"","populatejson":""},{"key":"dashboard","value":"fa fa-dashboard","groupkey":"","populatejson":""},{"key":"dashcube","value":"fa fa-dashcube","groupkey":"","populatejson":""},{"key":"database","value":"fa fa-database","groupkey":"","populatejson":""},{"key":"deaf","value":"fa fa-deaf","groupkey":"","populatejson":""},{"key":"deafness","value":"fa fa-deafness","groupkey":"","populatejson":""},{"key":"dedent","value":"fa fa-dedent","groupkey":"","populatejson":""},{"key":"delicious","value":"fa fa-delicious","groupkey":"","populatejson":""},{"key":"desktop","value":"fa fa-desktop","groupkey":"","populatejson":""},{"key":"deviantart","value":"fa fa-deviantart","groupkey":"","populatejson":""},{"key":"diamond","value":"fa fa-diamond","groupkey":"","populatejson":""},{"key":"digg","value":"fa fa-digg","groupkey":"","populatejson":""},{"key":"dollar","value":"fa fa-dollar","groupkey":"","populatejson":""},{"key":"dot-circle-o","value":"fa fa-dot-circle-o","groupkey":"","populatejson":""},{"key":"download","value":"fa fa-download","groupkey":"","populatejson":""},{"key":"dribbble","value":"fa fa-dribbble","groupkey":"","populatejson":""},{"key":"drivers-license","value":"fa fa-drivers-license","groupkey":"","populatejson":""},{"key":"drivers-license-o","value":"fa fa-drivers-license-o","groupkey":"","populatejson":""},{"key":"dropbox","value":"fa fa-dropbox","groupkey":"","populatejson":""},{"key":"drupal","value":"fa fa-drupal","groupkey":"","populatejson":""},{"key":"edge","value":"fa fa-edge","groupkey":"","populatejson":""},{"key":"edit","value":"fa fa-edit","groupkey":"","populatejson":""},{"key":"eercast","value":"fa fa-eercast","groupkey":"","populatejson":""},{"key":"eject","value":"fa fa-eject","groupkey":"","populatejson":""},{"key":"ellipsis-h","value":"fa fa-ellipsis-h","groupkey":"","populatejson":""},{"key":"ellipsis-v","value":"fa fa-ellipsis-v","groupkey":"","populatejson":""},{"key":"empire","value":"fa fa-empire","groupkey":"","populatejson":""},{"key":"envelope","value":"fa fa-envelope","groupkey":"","populatejson":""},{"key":"envelope-o","value":"fa fa-envelope-o","groupkey":"","populatejson":""},{"key":"envelope-open","value":"fa fa-envelope-open","groupkey":"","populatejson":""},{"key":"envelope-open-o","value":"fa fa-envelope-open-o","groupkey":"","populatejson":""},{"key":"envelope-square","value":"fa fa-envelope-square","groupkey":"","populatejson":""},{"key":"envira","value":"fa fa-envira","groupkey":"","populatejson":""},{"key":"eraser","value":"fa fa-eraser","groupkey":"","populatejson":""},{"key":"etsy","value":"fa fa-etsy","groupkey":"","populatejson":""},{"key":"eur","value":"fa fa-eur","groupkey":"","populatejson":""},{"key":"euro","value":"fa fa-euro","groupkey":"","populatejson":""},{"key":"exchange","value":"fa fa-exchange","groupkey":"","populatejson":""},{"key":"exclamation","value":"fa fa-exclamation","groupkey":"","populatejson":""},{"key":"exclamation-circle","value":"fa fa-exclamation-circle","groupkey":"","populatejson":""},{"key":"exclamation-triangle","value":"fa fa-exclamation-triangle","groupkey":"","populatejson":""},{"key":"expand","value":"fa fa-expand","groupkey":"","populatejson":""},{"key":"expeditedssl","value":"fa fa-expeditedssl","groupkey":"","populatejson":""},{"key":"external-link","value":"fa fa-external-link","groupkey":"","populatejson":""},{"key":"external-link-square","value":"fa fa-external-link-square","groupkey":"","populatejson":""},{"key":"eye","value":"fa fa-eye","groupkey":"","populatejson":""},{"key":"eye-slash","value":"fa fa-eye-slash","groupkey":"","populatejson":""},{"key":"eyedropper","value":"fa fa-eyedropper","groupkey":"","populatejson":""},{"key":"fa","value":"fa fa-fa","groupkey":"","populatejson":""},{"key":"facebook","value":"fa fa-facebook","groupkey":"","populatejson":""},{"key":"facebook-f","value":"fa fa-facebook-f","groupkey":"","populatejson":""},{"key":"facebook-official","value":"fa fa-facebook-official","groupkey":"","populatejson":""},{"key":"facebook-square","value":"fa fa-facebook-square","groupkey":"","populatejson":""},{"key":"fast-backward","value":"fa fa-fast-backward","groupkey":"","populatejson":""},{"key":"fast-forward","value":"fa fa-fast-forward","groupkey":"","populatejson":""},{"key":"fax","value":"fa fa-fax","groupkey":"","populatejson":""},{"key":"feed","value":"fa fa-feed","groupkey":"","populatejson":""},{"key":"female","value":"fa fa-female","groupkey":"","populatejson":""},{"key":"fighter-jet","value":"fa fa-fighter-jet","groupkey":"","populatejson":""},{"key":"file","value":"fa fa-file","groupkey":"","populatejson":""},{"key":"file-archive-o","value":"fa fa-file-archive-o","groupkey":"","populatejson":""},{"key":"file-audio-o","value":"fa fa-file-audio-o","groupkey":"","populatejson":""},{"key":"file-code-o","value":"fa fa-file-code-o","groupkey":"","populatejson":""},{"key":"file-excel-o","value":"fa fa-file-excel-o","groupkey":"","populatejson":""},{"key":"file-image-o","value":"fa fa-file-image-o","groupkey":"","populatejson":""},{"key":"file-movie-o","value":"fa fa-file-movie-o","groupkey":"","populatejson":""},{"key":"file-o","value":"fa fa-file-o","groupkey":"","populatejson":""},{"key":"file-pdf-o","value":"fa fa-file-pdf-o","groupkey":"","populatejson":""},{"key":"file-photo-o","value":"fa fa-file-photo-o","groupkey":"","populatejson":""},{"key":"file-picture-o","value":"fa fa-file-picture-o","groupkey":"","populatejson":""},{"key":"file-powerpoint-o","value":"fa fa-file-powerpoint-o","groupkey":"","populatejson":""},{"key":"file-sound-o","value":"fa fa-file-sound-o","groupkey":"","populatejson":""},{"key":"file-text","value":"fa fa-file-text","groupkey":"","populatejson":""},{"key":"file-text-o","value":"fa fa-file-text-o","groupkey":"","populatejson":""},{"key":"file-video-o","value":"fa fa-file-video-o","groupkey":"","populatejson":""},{"key":"file-word-o","value":"fa fa-file-word-o","groupkey":"","populatejson":""},{"key":"file-zip-o","value":"fa fa-file-zip-o","groupkey":"","populatejson":""},{"key":"files-o","value":"fa fa-files-o","groupkey":"","populatejson":""},{"key":"film","value":"fa fa-film","groupkey":"","populatejson":""},{"key":"filter","value":"fa fa-filter","groupkey":"","populatejson":""},{"key":"fire","value":"fa fa-fire","groupkey":"","populatejson":""},{"key":"fire-extinguisher","value":"fa fa-fire-extinguisher","groupkey":"","populatejson":""},{"key":"firefox","value":"fa fa-firefox","groupkey":"","populatejson":""},{"key":"first-order","value":"fa fa-first-order","groupkey":"","populatejson":""},{"key":"flag","value":"fa fa-flag","groupkey":"","populatejson":""},{"key":"flag-checkered","value":"fa fa-flag-checkered","groupkey":"","populatejson":""},{"key":"flag-o","value":"fa fa-flag-o","groupkey":"","populatejson":""},{"key":"flash","value":"fa fa-flash","groupkey":"","populatejson":""},{"key":"flask","value":"fa fa-flask","groupkey":"","populatejson":""},{"key":"flickr","value":"fa fa-flickr","groupkey":"","populatejson":""},{"key":"floppy-o","value":"fa fa-floppy-o","groupkey":"","populatejson":""},{"key":"folder","value":"fa fa-folder","groupkey":"","populatejson":""},{"key":"folder-o","value":"fa fa-folder-o","groupkey":"","populatejson":""},{"key":"folder-open","value":"fa fa-folder-open","groupkey":"","populatejson":""},{"key":"folder-open-o","value":"fa fa-folder-open-o","groupkey":"","populatejson":""},{"key":"font","value":"fa fa-font","groupkey":"","populatejson":""},{"key":"font-awesome","value":"fa fa-font-awesome","groupkey":"","populatejson":""},{"key":"fonticons","value":"fa fa-fonticons","groupkey":"","populatejson":""},{"key":"fort-awesome","value":"fa fa-fort-awesome","groupkey":"","populatejson":""},{"key":"forumbee","value":"fa fa-forumbee","groupkey":"","populatejson":""},{"key":"forward","value":"fa fa-forward","groupkey":"","populatejson":""},{"key":"foursquare","value":"fa fa-foursquare","groupkey":"","populatejson":""},{"key":"free-code-camp","value":"fa fa-free-code-camp","groupkey":"","populatejson":""},{"key":"frown-o","value":"fa fa-frown-o","groupkey":"","populatejson":""},{"key":"futbol-o","value":"fa fa-futbol-o","groupkey":"","populatejson":""},{"key":"gamepad","value":"fa fa-gamepad","groupkey":"","populatejson":""},{"key":"gavel","value":"fa fa-gavel","groupkey":"","populatejson":""},{"key":"gbp","value":"fa fa-gbp","groupkey":"","populatejson":""},{"key":"ge","value":"fa fa-ge","groupkey":"","populatejson":""},{"key":"gear","value":"fa fa-gear","groupkey":"","populatejson":""},{"key":"gears","value":"fa fa-gears","groupkey":"","populatejson":""},{"key":"genderless","value":"fa fa-genderless","groupkey":"","populatejson":""},{"key":"get-pocket","value":"fa fa-get-pocket","groupkey":"","populatejson":""},{"key":"gg","value":"fa fa-gg","groupkey":"","populatejson":""},{"key":"gg-circle","value":"fa fa-gg-circle","groupkey":"","populatejson":""},{"key":"gift","value":"fa fa-gift","groupkey":"","populatejson":""},{"key":"git","value":"fa fa-git","groupkey":"","populatejson":""},{"key":"git-square","value":"fa fa-git-square","groupkey":"","populatejson":""},{"key":"github","value":"fa fa-github","groupkey":"","populatejson":""},{"key":"github-alt","value":"fa fa-github-alt","groupkey":"","populatejson":""},{"key":"github-square","value":"fa fa-github-square","groupkey":"","populatejson":""},{"key":"gitlab","value":"fa fa-gitlab","groupkey":"","populatejson":""},{"key":"gittip","value":"fa fa-gittip","groupkey":"","populatejson":""},{"key":"glass","value":"fa fa-glass","groupkey":"","populatejson":""},{"key":"glide","value":"fa fa-glide","groupkey":"","populatejson":""},{"key":"glide-g","value":"fa fa-glide-g","groupkey":"","populatejson":""},{"key":"globe","value":"fa fa-globe","groupkey":"","populatejson":""},{"key":"google","value":"fa fa-google","groupkey":"","populatejson":""},{"key":"google-plus","value":"fa fa-google-plus","groupkey":"","populatejson":""},{"key":"google-plus-circle","value":"fa fa-google-plus-circle","groupkey":"","populatejson":""},{"key":"google-plus-official","value":"fa fa-google-plus-official","groupkey":"","populatejson":""},{"key":"google-plus-square","value":"fa fa-google-plus-square","groupkey":"","populatejson":""},{"key":"google-wallet","value":"fa fa-google-wallet","groupkey":"","populatejson":""},{"key":"graduation-cap","value":"fa fa-graduation-cap","groupkey":"","populatejson":""},{"key":"gratipay","value":"fa fa-gratipay","groupkey":"","populatejson":""},{"key":"grav","value":"fa fa-grav","groupkey":"","populatejson":""},{"key":"group","value":"fa fa-group","groupkey":"","populatejson":""},{"key":"h-square","value":"fa fa-h-square","groupkey":"","populatejson":""},{"key":"hacker-news","value":"fa fa-hacker-news","groupkey":"","populatejson":""},{"key":"hand-grab-o","value":"fa fa-hand-grab-o","groupkey":"","populatejson":""},{"key":"hand-lizard-o","value":"fa fa-hand-lizard-o","groupkey":"","populatejson":""},{"key":"hand-o-down","value":"fa fa-hand-o-down","groupkey":"","populatejson":""},{"key":"hand-o-left","value":"fa fa-hand-o-left","groupkey":"","populatejson":""},{"key":"hand-o-right","value":"fa fa-hand-o-right","groupkey":"","populatejson":""},{"key":"hand-o-up","value":"fa fa-hand-o-up","groupkey":"","populatejson":""},{"key":"hand-paper-o","value":"fa fa-hand-paper-o","groupkey":"","populatejson":""},{"key":"hand-peace-o","value":"fa fa-hand-peace-o","groupkey":"","populatejson":""},{"key":"hand-pointer-o","value":"fa fa-hand-pointer-o","groupkey":"","populatejson":""},{"key":"hand-rock-o","value":"fa fa-hand-rock-o","groupkey":"","populatejson":""},{"key":"hand-scissors-o","value":"fa fa-hand-scissors-o","groupkey":"","populatejson":""},{"key":"hand-spock-o","value":"fa fa-hand-spock-o","groupkey":"","populatejson":""},{"key":"hand-stop-o","value":"fa fa-hand-stop-o","groupkey":"","populatejson":""},{"key":"handshake-o","value":"fa fa-handshake-o","groupkey":"","populatejson":""},{"key":"hard-of-hearing","value":"fa fa-hard-of-hearing","groupkey":"","populatejson":""},{"key":"hashtag","value":"fa fa-hashtag","groupkey":"","populatejson":""},{"key":"hdd-o","value":"fa fa-hdd-o","groupkey":"","populatejson":""},{"key":"header","value":"fa fa-header","groupkey":"","populatejson":""},{"key":"headphones","value":"fa fa-headphones","groupkey":"","populatejson":""},{"key":"heart","value":"fa fa-heart","groupkey":"","populatejson":""},{"key":"heart-o","value":"fa fa-heart-o","groupkey":"","populatejson":""},{"key":"heartbeat","value":"fa fa-heartbeat","groupkey":"","populatejson":""},{"key":"history","value":"fa fa-history","groupkey":"","populatejson":""},{"key":"home","value":"fa fa-home","groupkey":"","populatejson":""},{"key":"hospital-o","value":"fa fa-hospital-o","groupkey":"","populatejson":""},{"key":"hotel","value":"fa fa-hotel","groupkey":"","populatejson":""},{"key":"hourglass","value":"fa fa-hourglass","groupkey":"","populatejson":""},{"key":"hourglass-1","value":"fa fa-hourglass-1","groupkey":"","populatejson":""},{"key":"hourglass-2","value":"fa fa-hourglass-2","groupkey":"","populatejson":""},{"key":"hourglass-3","value":"fa fa-hourglass-3","groupkey":"","populatejson":""},{"key":"hourglass-end","value":"fa fa-hourglass-end","groupkey":"","populatejson":""},{"key":"hourglass-half","value":"fa fa-hourglass-half","groupkey":"","populatejson":""},{"key":"hourglass-o","value":"fa fa-hourglass-o","groupkey":"","populatejson":""},{"key":"hourglass-start","value":"fa fa-hourglass-start","groupkey":"","populatejson":""},{"key":"houzz","value":"fa fa-houzz","groupkey":"","populatejson":""},{"key":"html5","value":"fa fa-html5","groupkey":"","populatejson":""},{"key":"i-cursor","value":"fa fa-i-cursor","groupkey":"","populatejson":""},{"key":"id-badge","value":"fa fa-id-badge","groupkey":"","populatejson":""},{"key":"id-card","value":"fa fa-id-card","groupkey":"","populatejson":""},{"key":"id-card-o","value":"fa fa-id-card-o","groupkey":"","populatejson":""},{"key":"ils","value":"fa fa-ils","groupkey":"","populatejson":""},{"key":"image","value":"fa fa-image","groupkey":"","populatejson":""},{"key":"imdb","value":"fa fa-imdb","groupkey":"","populatejson":""},{"key":"inbox","value":"fa fa-inbox","groupkey":"","populatejson":""},{"key":"indent","value":"fa fa-indent","groupkey":"","populatejson":""},{"key":"industry","value":"fa fa-industry","groupkey":"","populatejson":""},{"key":"info","value":"fa fa-info","groupkey":"","populatejson":""},{"key":"info-circle","value":"fa fa-info-circle","groupkey":"","populatejson":""},{"key":"inr","value":"fa fa-inr","groupkey":"","populatejson":""},{"key":"instagram","value":"fa fa-instagram","groupkey":"","populatejson":""},{"key":"institution","value":"fa fa-institution","groupkey":"","populatejson":""},{"key":"internet-explorer","value":"fa fa-internet-explorer","groupkey":"","populatejson":""},{"key":"intersex","value":"fa fa-intersex","groupkey":"","populatejson":""},{"key":"ioxhost","value":"fa fa-ioxhost","groupkey":"","populatejson":""},{"key":"italic","value":"fa fa-italic","groupkey":"","populatejson":""},{"key":"joomla","value":"fa fa-joomla","groupkey":"","populatejson":""},{"key":"jpy","value":"fa fa-jpy","groupkey":"","populatejson":""},{"key":"jsfiddle","value":"fa fa-jsfiddle","groupkey":"","populatejson":""},{"key":"key","value":"fa fa-key","groupkey":"","populatejson":""},{"key":"keyboard-o","value":"fa fa-keyboard-o","groupkey":"","populatejson":""},{"key":"krw","value":"fa fa-krw","groupkey":"","populatejson":""},{"key":"language","value":"fa fa-language","groupkey":"","populatejson":""},{"key":"laptop","value":"fa fa-laptop","groupkey":"","populatejson":""},{"key":"lastfm","value":"fa fa-lastfm","groupkey":"","populatejson":""},{"key":"lastfm-square","value":"fa fa-lastfm-square","groupkey":"","populatejson":""},{"key":"leaf","value":"fa fa-leaf","groupkey":"","populatejson":""},{"key":"leanpub","value":"fa fa-leanpub","groupkey":"","populatejson":""},{"key":"legal","value":"fa fa-legal","groupkey":"","populatejson":""},{"key":"lemon-o","value":"fa fa-lemon-o","groupkey":"","populatejson":""},{"key":"level-down","value":"fa fa-level-down","groupkey":"","populatejson":""},{"key":"level-up","value":"fa fa-level-up","groupkey":"","populatejson":""},{"key":"life-bouy","value":"fa fa-life-bouy","groupkey":"","populatejson":""},{"key":"life-buoy","value":"fa fa-life-buoy","groupkey":"","populatejson":""},{"key":"life-ring","value":"fa fa-life-ring","groupkey":"","populatejson":""},{"key":"life-saver","value":"fa fa-life-saver","groupkey":"","populatejson":""},{"key":"lightbulb-o","value":"fa fa-lightbulb-o","groupkey":"","populatejson":""},{"key":"line-chart","value":"fa fa-line-chart","groupkey":"","populatejson":""},{"key":"link","value":"fa fa-link","groupkey":"","populatejson":""},{"key":"linkedin","value":"fa fa-linkedin","groupkey":"","populatejson":""},{"key":"linkedin-square","value":"fa fa-linkedin-square","groupkey":"","populatejson":""},{"key":"linode","value":"fa fa-linode","groupkey":"","populatejson":""},{"key":"linux","value":"fa fa-linux","groupkey":"","populatejson":""},{"key":"list","value":"fa fa-list","groupkey":"","populatejson":""},{"key":"list-alt","value":"fa fa-list-alt","groupkey":"","populatejson":""},{"key":"list-ol","value":"fa fa-list-ol","groupkey":"","populatejson":""},{"key":"list-ul","value":"fa fa-list-ul","groupkey":"","populatejson":""},{"key":"location-arrow","value":"fa fa-location-arrow","groupkey":"","populatejson":""},{"key":"lock","value":"fa fa-lock","groupkey":"","populatejson":""},{"key":"long-arrow-down","value":"fa fa-long-arrow-down","groupkey":"","populatejson":""},{"key":"long-arrow-left","value":"fa fa-long-arrow-left","groupkey":"","populatejson":""},{"key":"long-arrow-right","value":"fa fa-long-arrow-right","groupkey":"","populatejson":""},{"key":"long-arrow-up","value":"fa fa-long-arrow-up","groupkey":"","populatejson":""},{"key":"low-vision","value":"fa fa-low-vision","groupkey":"","populatejson":""},{"key":"magic","value":"fa fa-magic","groupkey":"","populatejson":""},{"key":"magnet","value":"fa fa-magnet","groupkey":"","populatejson":""},{"key":"mail-forward","value":"fa fa-mail-forward","groupkey":"","populatejson":""},{"key":"mail-reply","value":"fa fa-mail-reply","groupkey":"","populatejson":""},{"key":"mail-reply-all","value":"fa fa-mail-reply-all","groupkey":"","populatejson":""},{"key":"male","value":"fa fa-male","groupkey":"","populatejson":""},{"key":"map","value":"fa fa-map","groupkey":"","populatejson":""},{"key":"map-marker","value":"fa fa-map-marker","groupkey":"","populatejson":""},{"key":"map-o","value":"fa fa-map-o","groupkey":"","populatejson":""},{"key":"map-pin","value":"fa fa-map-pin","groupkey":"","populatejson":""},{"key":"map-signs","value":"fa fa-map-signs","groupkey":"","populatejson":""},{"key":"mars","value":"fa fa-mars","groupkey":"","populatejson":""},{"key":"mars-double","value":"fa fa-mars-double","groupkey":"","populatejson":""},{"key":"mars-stroke","value":"fa fa-mars-stroke","groupkey":"","populatejson":""},{"key":"mars-stroke-h","value":"fa fa-mars-stroke-h","groupkey":"","populatejson":""},{"key":"mars-stroke-v","value":"fa fa-mars-stroke-v","groupkey":"","populatejson":""},{"key":"maxcdn","value":"fa fa-maxcdn","groupkey":"","populatejson":""},{"key":"meanpath","value":"fa fa-meanpath","groupkey":"","populatejson":""},{"key":"medium","value":"fa fa-medium","groupkey":"","populatejson":""},{"key":"medkit","value":"fa fa-medkit","groupkey":"","populatejson":""},{"key":"meetup","value":"fa fa-meetup","groupkey":"","populatejson":""},{"key":"meh-o","value":"fa fa-meh-o","groupkey":"","populatejson":""},{"key":"mercury","value":"fa fa-mercury","groupkey":"","populatejson":""},{"key":"microchip","value":"fa fa-microchip","groupkey":"","populatejson":""},{"key":"microphone","value":"fa fa-microphone","groupkey":"","populatejson":""},{"key":"microphone-slash","value":"fa fa-microphone-slash","groupkey":"","populatejson":""},{"key":"minus","value":"fa fa-minus","groupkey":"","populatejson":""},{"key":"minus-circle","value":"fa fa-minus-circle","groupkey":"","populatejson":""},{"key":"minus-square","value":"fa fa-minus-square","groupkey":"","populatejson":""},{"key":"minus-square-o","value":"fa fa-minus-square-o","groupkey":"","populatejson":""},{"key":"mixcloud","value":"fa fa-mixcloud","groupkey":"","populatejson":""},{"key":"mobile","value":"fa fa-mobile","groupkey":"","populatejson":""},{"key":"mobile-phone","value":"fa fa-mobile-phone","groupkey":"","populatejson":""},{"key":"modx","value":"fa fa-modx","groupkey":"","populatejson":""},{"key":"money","value":"fa fa-money","groupkey":"","populatejson":""},{"key":"moon-o","value":"fa fa-moon-o","groupkey":"","populatejson":""},{"key":"mortar-board","value":"fa fa-mortar-board","groupkey":"","populatejson":""},{"key":"motorcycle","value":"fa fa-motorcycle","groupkey":"","populatejson":""},{"key":"mouse-pointer","value":"fa fa-mouse-pointer","groupkey":"","populatejson":""},{"key":"music","value":"fa fa-music","groupkey":"","populatejson":""},{"key":"navicon","value":"fa fa-navicon","groupkey":"","populatejson":""},{"key":"neuter","value":"fa fa-neuter","groupkey":"","populatejson":""},{"key":"newspaper-o","value":"fa fa-newspaper-o","groupkey":"","populatejson":""},{"key":"object-group","value":"fa fa-object-group","groupkey":"","populatejson":""},{"key":"object-ungroup","value":"fa fa-object-ungroup","groupkey":"","populatejson":""},{"key":"odnoklassniki","value":"fa fa-odnoklassniki","groupkey":"","populatejson":""},{"key":"odnoklassniki-square","value":"fa fa-odnoklassniki-square","groupkey":"","populatejson":""},{"key":"opencart","value":"fa fa-opencart","groupkey":"","populatejson":""},{"key":"openid","value":"fa fa-openid","groupkey":"","populatejson":""},{"key":"opera","value":"fa fa-opera","groupkey":"","populatejson":""},{"key":"optin-monster","value":"fa fa-optin-monster","groupkey":"","populatejson":""},{"key":"outdent","value":"fa fa-outdent","groupkey":"","populatejson":""},{"key":"pagelines","value":"fa fa-pagelines","groupkey":"","populatejson":""},{"key":"paint-brush","value":"fa fa-paint-brush","groupkey":"","populatejson":""},{"key":"paper-plane","value":"fa fa-paper-plane","groupkey":"","populatejson":""},{"key":"paper-plane-o","value":"fa fa-paper-plane-o","groupkey":"","populatejson":""},{"key":"paperclip","value":"fa fa-paperclip","groupkey":"","populatejson":""},{"key":"paragraph","value":"fa fa-paragraph","groupkey":"","populatejson":""},{"key":"paste","value":"fa fa-paste","groupkey":"","populatejson":""},{"key":"pause","value":"fa fa-pause","groupkey":"","populatejson":""},{"key":"pause-circle","value":"fa fa-pause-circle","groupkey":"","populatejson":""},{"key":"pause-circle-o","value":"fa fa-pause-circle-o","groupkey":"","populatejson":""},{"key":"paw","value":"fa fa-paw","groupkey":"","populatejson":""},{"key":"paypal","value":"fa fa-paypal","groupkey":"","populatejson":""},{"key":"pencil","value":"fa fa-pencil","groupkey":"","populatejson":""},{"key":"pencil-square","value":"fa fa-pencil-square","groupkey":"","populatejson":""},{"key":"pencil-square-o","value":"fa fa-pencil-square-o","groupkey":"","populatejson":""},{"key":"percent","value":"fa fa-percent","groupkey":"","populatejson":""},{"key":"phone","value":"fa fa-phone","groupkey":"","populatejson":""},{"key":"phone-square","value":"fa fa-phone-square","groupkey":"","populatejson":""},{"key":"photo","value":"fa fa-photo","groupkey":"","populatejson":""},{"key":"picture-o","value":"fa fa-picture-o","groupkey":"","populatejson":""},{"key":"pie-chart","value":"fa fa-pie-chart","groupkey":"","populatejson":""},{"key":"pied-piper","value":"fa fa-pied-piper","groupkey":"","populatejson":""},{"key":"pied-piper-alt","value":"fa fa-pied-piper-alt","groupkey":"","populatejson":""},{"key":"pied-piper-pp","value":"fa fa-pied-piper-pp","groupkey":"","populatejson":""},{"key":"pinterest","value":"fa fa-pinterest","groupkey":"","populatejson":""},{"key":"pinterest-p","value":"fa fa-pinterest-p","groupkey":"","populatejson":""},{"key":"pinterest-square","value":"fa fa-pinterest-square","groupkey":"","populatejson":""},{"key":"plane","value":"fa fa-plane","groupkey":"","populatejson":""},{"key":"play","value":"fa fa-play","groupkey":"","populatejson":""},{"key":"play-circle","value":"fa fa-play-circle","groupkey":"","populatejson":""},{"key":"play-circle-o","value":"fa fa-play-circle-o","groupkey":"","populatejson":""},{"key":"plug","value":"fa fa-plug","groupkey":"","populatejson":""},{"key":"plus","value":"fa fa-plus","groupkey":"","populatejson":""},{"key":"plus-circle","value":"fa fa-plus-circle","groupkey":"","populatejson":""},{"key":"plus-square","value":"fa fa-plus-square","groupkey":"","populatejson":""},{"key":"plus-square-o","value":"fa fa-plus-square-o","groupkey":"","populatejson":""},{"key":"podcast","value":"fa fa-podcast","groupkey":"","populatejson":""},{"key":"power-off","value":"fa fa-power-off","groupkey":"","populatejson":""},{"key":"print","value":"fa fa-print","groupkey":"","populatejson":""},{"key":"product-hunt","value":"fa fa-product-hunt","groupkey":"","populatejson":""},{"key":"puzzle-piece","value":"fa fa-puzzle-piece","groupkey":"","populatejson":""},{"key":"qq","value":"fa fa-qq","groupkey":"","populatejson":""},{"key":"qrcode","value":"fa fa-qrcode","groupkey":"","populatejson":""},{"key":"question","value":"fa fa-question","groupkey":"","populatejson":""},{"key":"question-circle","value":"fa fa-question-circle","groupkey":"","populatejson":""},{"key":"question-circle-o","value":"fa fa-question-circle-o","groupkey":"","populatejson":""},{"key":"quora","value":"fa fa-quora","groupkey":"","populatejson":""},{"key":"quote-left","value":"fa fa-quote-left","groupkey":"","populatejson":""},{"key":"quote-right","value":"fa fa-quote-right","groupkey":"","populatejson":""},{"key":"ra","value":"fa fa-ra","groupkey":"","populatejson":""},{"key":"random","value":"fa fa-random","groupkey":"","populatejson":""},{"key":"ravelry","value":"fa fa-ravelry","groupkey":"","populatejson":""},{"key":"rebel","value":"fa fa-rebel","groupkey":"","populatejson":""},{"key":"recycle","value":"fa fa-recycle","groupkey":"","populatejson":""},{"key":"reddit","value":"fa fa-reddit","groupkey":"","populatejson":""},{"key":"reddit-alien","value":"fa fa-reddit-alien","groupkey":"","populatejson":""},{"key":"reddit-square","value":"fa fa-reddit-square","groupkey":"","populatejson":""},{"key":"refresh","value":"fa fa-refresh","groupkey":"","populatejson":""},{"key":"registered","value":"fa fa-registered","groupkey":"","populatejson":""},{"key":"remove","value":"fa fa-remove","groupkey":"","populatejson":""},{"key":"renren","value":"fa fa-renren","groupkey":"","populatejson":""},{"key":"reorder","value":"fa fa-reorder","groupkey":"","populatejson":""},{"key":"repeat","value":"fa fa-repeat","groupkey":"","populatejson":""},{"key":"reply","value":"fa fa-reply","groupkey":"","populatejson":""},{"key":"reply-all","value":"fa fa-reply-all","groupkey":"","populatejson":""},{"key":"resistance","value":"fa fa-resistance","groupkey":"","populatejson":""},{"key":"retweet","value":"fa fa-retweet","groupkey":"","populatejson":""},{"key":"rmb","value":"fa fa-rmb","groupkey":"","populatejson":""},{"key":"road","value":"fa fa-road","groupkey":"","populatejson":""},{"key":"rocket","value":"fa fa-rocket","groupkey":"","populatejson":""},{"key":"rotate-left","value":"fa fa-rotate-left","groupkey":"","populatejson":""},{"key":"rotate-right","value":"fa fa-rotate-right","groupkey":"","populatejson":""},{"key":"rouble","value":"fa fa-rouble","groupkey":"","populatejson":""},{"key":"rss","value":"fa fa-rss","groupkey":"","populatejson":""},{"key":"rss-square","value":"fa fa-rss-square","groupkey":"","populatejson":""},{"key":"rub","value":"fa fa-rub","groupkey":"","populatejson":""},{"key":"ruble","value":"fa fa-ruble","groupkey":"","populatejson":""},{"key":"rupee","value":"fa fa-rupee","groupkey":"","populatejson":""},{"key":"s15","value":"fa fa-s15","groupkey":"","populatejson":""},{"key":"safari","value":"fa fa-safari","groupkey":"","populatejson":""},{"key":"save","value":"fa fa-save","groupkey":"","populatejson":""},{"key":"scissors","value":"fa fa-scissors","groupkey":"","populatejson":""},{"key":"scribd","value":"fa fa-scribd","groupkey":"","populatejson":""},{"key":"search","value":"fa fa-search","groupkey":"","populatejson":""},{"key":"search-minus","value":"fa fa-search-minus","groupkey":"","populatejson":""},{"key":"search-plus","value":"fa fa-search-plus","groupkey":"","populatejson":""},{"key":"sellsy","value":"fa fa-sellsy","groupkey":"","populatejson":""},{"key":"send","value":"fa fa-send","groupkey":"","populatejson":""},{"key":"send-o","value":"fa fa-send-o","groupkey":"","populatejson":""},{"key":"server","value":"fa fa-server","groupkey":"","populatejson":""},{"key":"share","value":"fa fa-share","groupkey":"","populatejson":""},{"key":"share-alt","value":"fa fa-share-alt","groupkey":"","populatejson":""},{"key":"share-alt-square","value":"fa fa-share-alt-square","groupkey":"","populatejson":""},{"key":"share-square","value":"fa fa-share-square","groupkey":"","populatejson":""},{"key":"share-square-o","value":"fa fa-share-square-o","groupkey":"","populatejson":""},{"key":"shekel","value":"fa fa-shekel","groupkey":"","populatejson":""},{"key":"sheqel","value":"fa fa-sheqel","groupkey":"","populatejson":""},{"key":"shield","value":"fa fa-shield","groupkey":"","populatejson":""},{"key":"ship","value":"fa fa-ship","groupkey":"","populatejson":""},{"key":"shirtsinbulk","value":"fa fa-shirtsinbulk","groupkey":"","populatejson":""},{"key":"shopping-bag","value":"fa fa-shopping-bag","groupkey":"","populatejson":""},{"key":"shopping-basket","value":"fa fa-shopping-basket","groupkey":"","populatejson":""},{"key":"shopping-cart","value":"fa fa-shopping-cart","groupkey":"","populatejson":""},{"key":"shower","value":"fa fa-shower","groupkey":"","populatejson":""},{"key":"sign-in","value":"fa fa-sign-in","groupkey":"","populatejson":""},{"key":"sign-language","value":"fa fa-sign-language","groupkey":"","populatejson":""},{"key":"sign-out","value":"fa fa-sign-out","groupkey":"","populatejson":""},{"key":"signal","value":"fa fa-signal","groupkey":"","populatejson":""},{"key":"signing","value":"fa fa-signing","groupkey":"","populatejson":""},{"key":"simplybuilt","value":"fa fa-simplybuilt","groupkey":"","populatejson":""},{"key":"sitemap","value":"fa fa-sitemap","groupkey":"","populatejson":""},{"key":"skyatlas","value":"fa fa-skyatlas","groupkey":"","populatejson":""},{"key":"skype","value":"fa fa-skype","groupkey":"","populatejson":""},{"key":"slack","value":"fa fa-slack","groupkey":"","populatejson":""},{"key":"sliders","value":"fa fa-sliders","groupkey":"","populatejson":""},{"key":"slideshare","value":"fa fa-slideshare","groupkey":"","populatejson":""},{"key":"smile-o","value":"fa fa-smile-o","groupkey":"","populatejson":""},{"key":"snapchat","value":"fa fa-snapchat","groupkey":"","populatejson":""},{"key":"snapchat-ghost","value":"fa fa-snapchat-ghost","groupkey":"","populatejson":""},{"key":"snapchat-square","value":"fa fa-snapchat-square","groupkey":"","populatejson":""},{"key":"snowflake-o","value":"fa fa-snowflake-o","groupkey":"","populatejson":""},{"key":"soccer-ball-o","value":"fa fa-soccer-ball-o","groupkey":"","populatejson":""},{"key":"sort","value":"fa fa-sort","groupkey":"","populatejson":""},{"key":"sort-alpha-asc","value":"fa fa-sort-alpha-asc","groupkey":"","populatejson":""},{"key":"sort-alpha-desc","value":"fa fa-sort-alpha-desc","groupkey":"","populatejson":""},{"key":"sort-amount-asc","value":"fa fa-sort-amount-asc","groupkey":"","populatejson":""},{"key":"sort-amount-desc","value":"fa fa-sort-amount-desc","groupkey":"","populatejson":""},{"key":"sort-asc","value":"fa fa-sort-asc","groupkey":"","populatejson":""},{"key":"sort-desc","value":"fa fa-sort-desc","groupkey":"","populatejson":""},{"key":"sort-down","value":"fa fa-sort-down","groupkey":"","populatejson":""},{"key":"sort-numeric-asc","value":"fa fa-sort-numeric-asc","groupkey":"","populatejson":""},{"key":"sort-numeric-desc","value":"fa fa-sort-numeric-desc","groupkey":"","populatejson":""},{"key":"sort-up","value":"fa fa-sort-up","groupkey":"","populatejson":""},{"key":"soundcloud","value":"fa fa-soundcloud","groupkey":"","populatejson":""},{"key":"space-shuttle","value":"fa fa-space-shuttle","groupkey":"","populatejson":""},{"key":"spinner","value":"fa fa-spinner","groupkey":"","populatejson":""},{"key":"spoon","value":"fa fa-spoon","groupkey":"","populatejson":""},{"key":"spotify","value":"fa fa-spotify","groupkey":"","populatejson":""},{"key":"square","value":"fa fa-square","groupkey":"","populatejson":""},{"key":"square-o","value":"fa fa-square-o","groupkey":"","populatejson":""},{"key":"stack-exchange","value":"fa fa-stack-exchange","groupkey":"","populatejson":""},{"key":"stack-overflow","value":"fa fa-stack-overflow","groupkey":"","populatejson":""},{"key":"star","value":"fa fa-star","groupkey":"","populatejson":""},{"key":"star-half","value":"fa fa-star-half","groupkey":"","populatejson":""},{"key":"star-half-empty","value":"fa fa-star-half-empty","groupkey":"","populatejson":""},{"key":"star-half-full","value":"fa fa-star-half-full","groupkey":"","populatejson":""},{"key":"star-half-o","value":"fa fa-star-half-o","groupkey":"","populatejson":""},{"key":"star-o","value":"fa fa-star-o","groupkey":"","populatejson":""},{"key":"steam","value":"fa fa-steam","groupkey":"","populatejson":""},{"key":"steam-square","value":"fa fa-steam-square","groupkey":"","populatejson":""},{"key":"step-backward","value":"fa fa-step-backward","groupkey":"","populatejson":""},{"key":"step-forward","value":"fa fa-step-forward","groupkey":"","populatejson":""},{"key":"stethoscope","value":"fa fa-stethoscope","groupkey":"","populatejson":""},{"key":"sticky-note","value":"fa fa-sticky-note","groupkey":"","populatejson":""},{"key":"sticky-note-o","value":"fa fa-sticky-note-o","groupkey":"","populatejson":""},{"key":"stop","value":"fa fa-stop","groupkey":"","populatejson":""},{"key":"stop-circle","value":"fa fa-stop-circle","groupkey":"","populatejson":""},{"key":"stop-circle-o","value":"fa fa-stop-circle-o","groupkey":"","populatejson":""},{"key":"street-view","value":"fa fa-street-view","groupkey":"","populatejson":""},{"key":"strikethrough","value":"fa fa-strikethrough","groupkey":"","populatejson":""},{"key":"stumbleupon","value":"fa fa-stumbleupon","groupkey":"","populatejson":""},{"key":"stumbleupon-circle","value":"fa fa-stumbleupon-circle","groupkey":"","populatejson":""},{"key":"subscript","value":"fa fa-subscript","groupkey":"","populatejson":""},{"key":"subway","value":"fa fa-subway","groupkey":"","populatejson":""},{"key":"suitcase","value":"fa fa-suitcase","groupkey":"","populatejson":""},{"key":"sun-o","value":"fa fa-sun-o","groupkey":"","populatejson":""},{"key":"superpowers","value":"fa fa-superpowers","groupkey":"","populatejson":""},{"key":"superscript","value":"fa fa-superscript","groupkey":"","populatejson":""},{"key":"support","value":"fa fa-support","groupkey":"","populatejson":""},{"key":"table","value":"fa fa-table","groupkey":"","populatejson":""},{"key":"tablet","value":"fa fa-tablet","groupkey":"","populatejson":""},{"key":"tachometer","value":"fa fa-tachometer","groupkey":"","populatejson":""},{"key":"tag","value":"fa fa-tag","groupkey":"","populatejson":""},{"key":"tags","value":"fa fa-tags","groupkey":"","populatejson":""},{"key":"tasks","value":"fa fa-tasks","groupkey":"","populatejson":""},{"key":"taxi","value":"fa fa-taxi","groupkey":"","populatejson":""},{"key":"telegram","value":"fa fa-telegram","groupkey":"","populatejson":""},{"key":"television","value":"fa fa-television","groupkey":"","populatejson":""},{"key":"tencent-weibo","value":"fa fa-tencent-weibo","groupkey":"","populatejson":""},{"key":"terminal","value":"fa fa-terminal","groupkey":"","populatejson":""},{"key":"text-height","value":"fa fa-text-height","groupkey":"","populatejson":""},{"key":"text-width","value":"fa fa-text-width","groupkey":"","populatejson":""},{"key":"th","value":"fa fa-th","groupkey":"","populatejson":""},{"key":"th-large","value":"fa fa-th-large","groupkey":"","populatejson":""},{"key":"th-list","value":"fa fa-th-list","groupkey":"","populatejson":""},{"key":"themeisle","value":"fa fa-themeisle","groupkey":"","populatejson":""},{"key":"thermometer","value":"fa fa-thermometer","groupkey":"","populatejson":""},{"key":"thermometer-0","value":"fa fa-thermometer-0","groupkey":"","populatejson":""},{"key":"thermometer-1","value":"fa fa-thermometer-1","groupkey":"","populatejson":""},{"key":"thermometer-2","value":"fa fa-thermometer-2","groupkey":"","populatejson":""},{"key":"thermometer-3","value":"fa fa-thermometer-3","groupkey":"","populatejson":""},{"key":"thermometer-4","value":"fa fa-thermometer-4","groupkey":"","populatejson":""},{"key":"thermometer-empty","value":"fa fa-thermometer-empty","groupkey":"","populatejson":""},{"key":"thermometer-full","value":"fa fa-thermometer-full","groupkey":"","populatejson":""},{"key":"thermometer-half","value":"fa fa-thermometer-half","groupkey":"","populatejson":""},{"key":"thermometer-quarter","value":"fa fa-thermometer-quarter","groupkey":"","populatejson":""},{"key":"thermometer-three-quarters","value":"fa fa-thermometer-three-quarters","groupkey":"","populatejson":""},{"key":"thumb-tack","value":"fa fa-thumb-tack","groupkey":"","populatejson":""},{"key":"thumbs-down","value":"fa fa-thumbs-down","groupkey":"","populatejson":""},{"key":"thumbs-o-down","value":"fa fa-thumbs-o-down","groupkey":"","populatejson":""},{"key":"thumbs-o-up","value":"fa fa-thumbs-o-up","groupkey":"","populatejson":""},{"key":"thumbs-up","value":"fa fa-thumbs-up","groupkey":"","populatejson":""},{"key":"ticket","value":"fa fa-ticket","groupkey":"","populatejson":""},{"key":"times","value":"fa fa-times","groupkey":"","populatejson":""},{"key":"times-circle","value":"fa fa-times-circle","groupkey":"","populatejson":""},{"key":"times-circle-o","value":"fa fa-times-circle-o","groupkey":"","populatejson":""},{"key":"times-rectangle","value":"fa fa-times-rectangle","groupkey":"","populatejson":""},{"key":"times-rectangle-o","value":"fa fa-times-rectangle-o","groupkey":"","populatejson":""},{"key":"tint","value":"fa fa-tint","groupkey":"","populatejson":""},{"key":"toggle-down","value":"fa fa-toggle-down","groupkey":"","populatejson":""},{"key":"toggle-left","value":"fa fa-toggle-left","groupkey":"","populatejson":""},{"key":"toggle-off","value":"fa fa-toggle-off","groupkey":"","populatejson":""},{"key":"toggle-on","value":"fa fa-toggle-on","groupkey":"","populatejson":""},{"key":"toggle-right","value":"fa fa-toggle-right","groupkey":"","populatejson":""},{"key":"toggle-up","value":"fa fa-toggle-up","groupkey":"","populatejson":""},{"key":"trademark","value":"fa fa-trademark","groupkey":"","populatejson":""},{"key":"train","value":"fa fa-train","groupkey":"","populatejson":""},{"key":"transgender","value":"fa fa-transgender","groupkey":"","populatejson":""},{"key":"transgender-alt","value":"fa fa-transgender-alt","groupkey":"","populatejson":""},{"key":"trash","value":"fa fa-trash","groupkey":"","populatejson":""},{"key":"trash-o","value":"fa fa-trash-o","groupkey":"","populatejson":""},{"key":"tree","value":"fa fa-tree","groupkey":"","populatejson":""},{"key":"trello","value":"fa fa-trello","groupkey":"","populatejson":""},{"key":"tripadvisor","value":"fa fa-tripadvisor","groupkey":"","populatejson":""},{"key":"trophy","value":"fa fa-trophy","groupkey":"","populatejson":""},{"key":"truck","value":"fa fa-truck","groupkey":"","populatejson":""},{"key":"try","value":"fa fa-try","groupkey":"","populatejson":""},{"key":"tty","value":"fa fa-tty","groupkey":"","populatejson":""},{"key":"tumblr","value":"fa fa-tumblr","groupkey":"","populatejson":""},{"key":"tumblr-square","value":"fa fa-tumblr-square","groupkey":"","populatejson":""},{"key":"turkish-lira","value":"fa fa-turkish-lira","groupkey":"","populatejson":""},{"key":"tv","value":"fa fa-tv","groupkey":"","populatejson":""},{"key":"twitch","value":"fa fa-twitch","groupkey":"","populatejson":""},{"key":"twitter","value":"fa fa-twitter","groupkey":"","populatejson":""},{"key":"twitter-square","value":"fa fa-twitter-square","groupkey":"","populatejson":""},{"key":"umbrella","value":"fa fa-umbrella","groupkey":"","populatejson":""},{"key":"underline","value":"fa fa-underline","groupkey":"","populatejson":""},{"key":"undo","value":"fa fa-undo","groupkey":"","populatejson":""},{"key":"universal-access","value":"fa fa-universal-access","groupkey":"","populatejson":""},{"key":"university","value":"fa fa-university","groupkey":"","populatejson":""},{"key":"unlink","value":"fa fa-unlink","groupkey":"","populatejson":""},{"key":"unlock","value":"fa fa-unlock","groupkey":"","populatejson":""},{"key":"unlock-alt","value":"fa fa-unlock-alt","groupkey":"","populatejson":""},{"key":"unsorted","value":"fa fa-unsorted","groupkey":"","populatejson":""},{"key":"upload","value":"fa fa-upload","groupkey":"","populatejson":""},{"key":"usb","value":"fa fa-usb","groupkey":"","populatejson":""},{"key":"usd","value":"fa fa-usd","groupkey":"","populatejson":""},{"key":"user","value":"fa fa-user","groupkey":"","populatejson":""},{"key":"user-circle","value":"fa fa-user-circle","groupkey":"","populatejson":""},{"key":"user-circle-o","value":"fa fa-user-circle-o","groupkey":"","populatejson":""},{"key":"user-md","value":"fa fa-user-md","groupkey":"","populatejson":""},{"key":"user-o","value":"fa fa-user-o","groupkey":"","populatejson":""},{"key":"user-plus","value":"fa fa-user-plus","groupkey":"","populatejson":""},{"key":"user-secret","value":"fa fa-user-secret","groupkey":"","populatejson":""},{"key":"user-times","value":"fa fa-user-times","groupkey":"","populatejson":""},{"key":"users","value":"fa fa-users","groupkey":"","populatejson":""},{"key":"vcard","value":"fa fa-vcard","groupkey":"","populatejson":""},{"key":"vcard-o","value":"fa fa-vcard-o","groupkey":"","populatejson":""},{"key":"venus","value":"fa fa-venus","groupkey":"","populatejson":""},{"key":"venus-double","value":"fa fa-venus-double","groupkey":"","populatejson":""},{"key":"venus-mars","value":"fa fa-venus-mars","groupkey":"","populatejson":""},{"key":"viacoin","value":"fa fa-viacoin","groupkey":"","populatejson":""},{"key":"viadeo","value":"fa fa-viadeo","groupkey":"","populatejson":""},{"key":"viadeo-square","value":"fa fa-viadeo-square","groupkey":"","populatejson":""},{"key":"video-camera","value":"fa fa-video-camera","groupkey":"","populatejson":""},{"key":"vimeo","value":"fa fa-vimeo","groupkey":"","populatejson":""},{"key":"vimeo-square","value":"fa fa-vimeo-square","groupkey":"","populatejson":""},{"key":"vine","value":"fa fa-vine","groupkey":"","populatejson":""},{"key":"vk","value":"fa fa-vk","groupkey":"","populatejson":""},{"key":"volume-control-phone","value":"fa fa-volume-control-phone","groupkey":"","populatejson":""},{"key":"volume-down","value":"fa fa-volume-down","groupkey":"","populatejson":""},{"key":"volume-off","value":"fa fa-volume-off","groupkey":"","populatejson":""},{"key":"volume-up","value":"fa fa-volume-up","groupkey":"","populatejson":""},{"key":"warning","value":"fa fa-warning","groupkey":"","populatejson":""},{"key":"wechat","value":"fa fa-wechat","groupkey":"","populatejson":""},{"key":"weibo","value":"fa fa-weibo","groupkey":"","populatejson":""},{"key":"weixin","value":"fa fa-weixin","groupkey":"","populatejson":""},{"key":"whatsapp","value":"fa fa-whatsapp","groupkey":"","populatejson":""},{"key":"wheelchair","value":"fa fa-wheelchair","groupkey":"","populatejson":""},{"key":"wheelchair-alt","value":"fa fa-wheelchair-alt","groupkey":"","populatejson":""},{"key":"wifi","value":"fa fa-wifi","groupkey":"","populatejson":""},{"key":"wikipedia-w","value":"fa fa-wikipedia-w","groupkey":"","populatejson":""},{"key":"window-close","value":"fa fa-window-close","groupkey":"","populatejson":""},{"key":"window-close-o","value":"fa fa-window-close-o","groupkey":"","populatejson":""},{"key":"window-maximize","value":"fa fa-window-maximize","groupkey":"","populatejson":""},{"key":"window-minimize","value":"fa fa-window-minimize","groupkey":"","populatejson":""},{"key":"window-restore","value":"fa fa-window-restore","groupkey":"","populatejson":""},{"key":"windows","value":"fa fa-windows","groupkey":"","populatejson":""},{"key":"won","value":"fa fa-won","groupkey":"","populatejson":""},{"key":"wordpress","value":"fa fa-wordpress","groupkey":"","populatejson":""},{"key":"wpbeginner","value":"fa fa-wpbeginner","groupkey":"","populatejson":""},{"key":"wpexplorer","value":"fa fa-wpexplorer","groupkey":"","populatejson":""},{"key":"wpforms","value":"fa fa-wpforms","groupkey":"","populatejson":""},{"key":"wrench","value":"fa fa-wrench","groupkey":"","populatejson":""},{"key":"xing","value":"fa fa-xing","groupkey":"","populatejson":""},{"key":"xing-square","value":"fa fa-xing-square","groupkey":"","populatejson":""},{"key":"y-combinator","value":"fa fa-y-combinator","groupkey":"","populatejson":""},{"key":"y-combinator-square","value":"fa fa-y-combinator-square","groupkey":"","populatejson":""},{"key":"yahoo","value":"fa fa-yahoo","groupkey":"","populatejson":""},{"key":"yc","value":"fa fa-yc","groupkey":"","populatejson":""},{"key":"yc-square","value":"fa fa-yc-square","groupkey":"","populatejson":""},{"key":"yelp","value":"fa fa-yelp","groupkey":"","populatejson":""},{"key":"yen","value":"fa fa-yen","groupkey":"","populatejson":""},{"key":"yoast","value":"fa fa-yoast","groupkey":"","populatejson":""},{"key":"youtube","value":"fa fa-youtube","groupkey":"","populatejson":""},{"key":"youtube-play","value":"fa fa-youtube-play","groupkey":"","populatejson":""},{"key":"youtube-square","value":"fa fa-youtube-square","groupkey":"","populatejson":""},{"key":"quality","value":"flaticon-quality","groupkey":"","populatejson":""},{"key":"checklist","value":"flaticon-checklist","groupkey":"","populatejson":""},{"key":"hierarchy","value":"flaticon-hierarchy","groupkey":"","populatejson":""},{"key":"timeline","value":"flaticon-timeline","groupkey":"","populatejson":""},{"key":"trophy","value":"flaticon-trophy","groupkey":"","populatejson":""},{"key":"graph","value":"flaticon-graph","groupkey":"","populatejson":""},{"key":"businessman","value":"flaticon-businessman","groupkey":"","populatejson":""},{"key":"briefcase","value":"flaticon-briefcase","groupkey":"","populatejson":""},{"key":"job-search","value":"flaticon-job-search","groupkey":"","populatejson":""},{"key":"agenda","value":"flaticon-agenda","groupkey":"","populatejson":""},{"key":"circle","value":"flaticon-circle","groupkey":"","populatejson":""},{"key":"emoji","value":"flaticon-emoji","groupkey":"","populatejson":""},{"key":"dislike","value":"flaticon-dislike","groupkey":"","populatejson":""},{"key":"money","value":"flaticon-money","groupkey":"","populatejson":""},{"key":"mute-emoticon-square-face","value":"flaticon-mute-emoticon-square-face","groupkey":"","populatejson":""},{"key":"filter","value":"flaticon-filter","groupkey":"","populatejson":""},{"key":"settings-48px","value":"flaticon-settings-48px","groupkey":"","populatejson":""},{"key":"settings-power-48px","value":"flaticon-settings-power-48px","groupkey":"","populatejson":""}],"storejsonnode":false,"selectiontype":"single","defaulttext":"Select","selectalltext":"Select All","unselectalltext":"UnSelect All","enablesearchfilter":true,"pullRight":false,"selectionLimit":null,"closeOnSelect":true,"maxHeight":"400px","isLazyLoad":false,"from":"from","search":"","dynamictitlemaxitems":9999999,"showcheckall":false,"showuncheckall":false,"id":"e0d6f0b1-2c8c-ad4f-f077-9c614f4537e9","filterresult":false,"uuid":4617392543488},{"key":"width","Name":"Dropdown 2","label":"Select Width","placeholder":"Select Width","icon":"fa fa-chevron-circle-down","type":"dropdown2","width":"12","order":2,"require":false,"showinlist":true,"haschildren":false,"isTableView":false,"hasdatasource":false,"allowbindingwithcontrols":false,"bindingwithothercontrols":[],"refreshfromparent":false,"parentcontrolkey":"","apifieldforparentcontrol":"","addinfilter":false,"filterheader":"","autoselectfirstvalue":false,"textfield":"key","valuefield":"value","apiurl":"","ApiParam":[],"optionlist":[{"key":"1","id":"9e4e935e-5612-fdc0-4e58-21ab4e2ba352","value":"1","groupkey":"","populatejson":""},{"key":"2","id":"b7f2ad1a-29bc-bc32-d23b-06dc573753ec","value":"2","groupkey":"","populatejson":""},{"key":"3","id":"a4aa7341-9472-8c7a-b8e0-aaa573b77c9e","value":"3","groupkey":"","populatejson":""},{"key":"4","id":"85b24097-a170-03c5-b048-fb0eb52c40f8","value":"4","groupkey":"","populatejson":""},{"key":"5","id":"6e0e1d10-878a-e22c-829b-5c5b4aeb4377","value":"5","groupkey":"","populatejson":""},{"key":"6","id":"63b32f72-f46d-dc46-e442-95644d353735","value":"6","groupkey":"","populatejson":""},{"key":"7","id":"0ebe53a5-31ea-9347-3ee1-e9215663ef75","value":"7","groupkey":"","populatejson":""},{"key":"8","id":"ae452d94-f309-bfeb-8351-6d509ce4a6cc","value":"8","groupkey":"","populatejson":""},{"key":"9","id":"a2b3c43b-e9dc-16ed-445b-09e2a0513392","value":"9","groupkey":"","populatejson":""},{"key":"10","id":"96d3e2fa-f1fc-b600-bc50-6da29d418dc4","value":"10","groupkey":"","populatejson":""},{"key":"11","id":"dae119db-d54b-c846-26e2-ceae4736b24b","value":"11","groupkey":"","populatejson":""},{"key":"12","id":"5cb3bd08-2375-a6cd-f31b-6e68cf77d2ae","value":"12","groupkey":"","populatejson":""},{"key":"Auto","id":"fbace6fe-d7d-6ec3-a34e-cf333a85b98f","value":"auto","groupkey":"","populatejson":""}],"storejsonnode":false,"selectiontype":"single","defaulttext":"Select","selectalltext":"Select All","unselectalltext":"UnSelect All","enablesearchfilter":false,"pullRight":false,"selectionLimit":null,"closeOnSelect":true,"maxHeight":"400px","isLazyLoad":false,"from":"from","search":"","dynamictitlemaxitems":9999999,"showcheckall":false,"showuncheckall":false,"id":"3a985ea3-dd3b-1525-8ce5-f927f46c6be0","filterresult":false,"uuid":9858742096123},{"key":"size","Name":"Dropdown 2","label":"Size","placeholder":"Size","icon":"fa fa-chevron-circle-down","type":"dropdown2","width":"12","order":3,"require":false,"showinlist":true,"haschildren":false,"isTableView":false,"hasdatasource":false,"allowbindingwithcontrols":false,"bindingwithothercontrols":[],"refreshfromparent":false,"parentcontrolkey":"","apifieldforparentcontrol":"","addinfilter":false,"filterheader":"","autoselectfirstvalue":false,"textfield":"key","valuefield":"value","apiurl":"","ApiParam":[],"optionlist":[{"key":"Small","id":"ece2c3de-5c9a-dda6-19f8-d4f2b1c6d36a","value":"sm","groupkey":"","populatejson":""},{"key":"Medium","id":"921c069d-958e-1dc8-fa8d-ef01cba1ab64","value":"md","groupkey":"","populatejson":""},{"key":"Large","id":"7fa1a4c7-d1b0-8d5f-a941-62e42234944b","value":"lg","groupkey":"","populatejson":""}],"storejsonnode":false,"selectiontype":"single","defaulttext":"Select","selectalltext":"Select All","unselectalltext":"UnSelect All","enablesearchfilter":false,"pullRight":false,"selectionLimit":null,"closeOnSelect":true,"maxHeight":"400px","isLazyLoad":false,"from":"from","search":"","dynamictitlemaxitems":9999999,"showcheckall":false,"showuncheckall":false,"id":"1f1d688f-aed5-e865-fed6-e39c8bebde5b","filterresult":false,"uuid":7662669115030},{"key":"buttontype","Name":"Dropdown 2","label":"Button Type","placeholder":"Button Type","icon":"fa fa-chevron-circle-down","type":"dropdown2","width":"12","order":4,"require":false,"showinlist":true,"haschildren":false,"isTableView":false,"hasdatasource":false,"allowbindingwithcontrols":false,"bindingwithothercontrols":[],"refreshfromparent":false,"parentcontrolkey":"","apifieldforparentcontrol":"","addinfilter":false,"filterheader":"","autoselectfirstvalue":false,"textfield":"key","valuefield":"value","apiurl":"","ApiParam":[],"optionlist":[{"key":"Primary","id":"2470b4d5-ef3e-ab50-25e5-e9bac3ae9062","value":"primary","groupkey":"","populatejson":""},{"key":"Secondary","id":"50e99d29-7ec0-d7de-cb82-573b1d60fee8","value":"secondary","groupkey":"","populatejson":""},{"key":"Success","id":"5b9dd722-9971-d896-6c96-d18ae7ac315a","value":"success","groupkey":"","populatejson":""},{"key":"Danger","id":"8e6c875f-4781-6b5a-279e-11e38b6c93a1","value":"danger","groupkey":"","populatejson":""},{"key":"Warning","id":"d4a3fc85-ae08-8baf-2a93-9bbad81de18b","value":"warning","groupkey":"","populatejson":""},{"key":"Info","id":"44b28a58-37b6-b17d-59e1-ffc886a707eb","value":"info","groupkey":"","populatejson":""},{"key":"Light","id":"54f24502-593f-eb6d-981a-b60bf4193ab6","value":"light","groupkey":"","populatejson":""},{"key":"Dark","id":"48df989e-d472-e778-5ec8-4d545f564291","value":"dark","groupkey":"","populatejson":""},{"key":"Link","id":"4d4b51dc-c10e-18ae-3019-06378f0b9d17","value":"link","groupkey":"","populatejson":""},{"key":"Outline Primary","id":"5af4a3b0-26ca-7e92-74ef-42d8c760d25d","value":"outline-primary","groupkey":"","populatejson":""},{"key":"Outline Secondary","id":"badf8555-fd43-fe96-79d2-310531a6fb05","value":"outline-secondary","groupkey":"","populatejson":""},{"key":"Outline Success","id":"61aa1ed9-270a-3764-fcb8-ad9872213b64","value":"outline-success","groupkey":"","populatejson":""},{"key":"Outline Danger","id":"170d5353-4d75-dbca-617d-32cd23b8233e","value":"outline-danger","groupkey":"","populatejson":""},{"key":"Outline Warning","id":"bc7393c8-d0a0-0247-dee4-5fbe0c28db38","value":"outline-warning","groupkey":"","populatejson":""},{"key":"Outline Info","id":"9e784e70-cb92-45fc-2880-8ac2cdf79113","value":"outline-info","groupkey":"","populatejson":""},{"key":"Outline Light","id":"6a51e07c-42b7-ebac-c0f4-9332f0122450","value":"outline-light","groupkey":"","populatejson":""},{"key":"Outline Dark","id":"6f113fc9-e748-0a45-4285-fdbfe8e2b4c0","value":"outline-dark","groupkey":"","populatejson":""}],"storejsonnode":false,"selectiontype":"single","defaulttext":"Select","selectalltext":"Select All","unselectalltext":"UnSelect All","enablesearchfilter":false,"pullRight":false,"selectionLimit":null,"closeOnSelect":true,"maxHeight":"400px","isLazyLoad":false,"from":"from","search":"","dynamictitlemaxitems":9999999,"showcheckall":false,"showuncheckall":false,"id":"472065f4-b33b-27f5-5428-2d9dba86ba13","filterresult":false,"uuid":8561451238818},{"id":"43935830-4785-4941-5cdd-2df165d09556","key":"coutomClass","Name":"Textbox","label":"Custom Class","placeholder":".p-1","icon":"fa fa-text-width","type":"textbox","width":"12","order":1,"require":false,"showinlist":true,"addinfilter":false,"filterheader":"","haschildren":false,"isTableView":false,"hasdatasource":false,"filterresult":false,"uuid":708230959089}],"uuid":293907173235,"require":false,"imageUrl":""}],"position":"left","showdetailpanel":true,"id":"0998dcc6-7343-1e99-ed44-45952ad2db6c","filterresult":false,"uuid":842769889170}],"ModelJson":{"key":"","titlemodel":"","subtitlemodel":"","icon":"","label":"","WebIcon":"","width":"","size":"","buttontype":"","coutomClass":"","id":""},"FilterModelJson":[],"FilterUIJson":{"filtertype":"None","filterAddform":"","ShowAddform":true,"addBtnText":"Add New","addBtnClass":"ml-2 btn-outline-primary btn-round","addBtnIcon":"fa fa-plus","ShowExport":false,"CustomFilter":false,"customfilterapimappingform":"","customfilterapimapping":[],"exportBtnText":"Export","exportBtnClass":"ml-2 btn-outline-primary btn-round","exportBtnIcon":"fa fa-file-excel-o","searchBtnClass":"btn-outline-secondary","searchBtnIcon":"fa fa-search","applyFilterBtnClass":"btn-outline-primary","applyFilterBtnIcon":"none","applyFilterBtnText":"Apply","filterBtnClass":"ml-2 btn-outline-secondary","filterBtnIcon":"fa fa-filter","filterBubble":"bg-danger","ShowImport":false,"importBtnText":"Import","importBtnClass":"ml-2 btn-outline-primary btn-round","importBtnIcon":"fa fa-cloud-upload","ExportColumns":[],"FilterApiEndpoint":"","FilterEndpointParams":[],"controls":[]},"IsDeleted":"false","Isactive":"true","CreateDate":"2018-06-28T15:29:27.1457768-04:00","UpdateDate":"2018-06-28T15:36:27.4107605-04:00"}